application_tracker/__init__.py
application_tracker/__main__.py
application_tracker/cli.py
application_tracker/config.py
application_tracker/database.py
application_tracker/tracker.py
application_tracker-0.1.0.dist-info/LICENSE
application_tracker-0.1.0.dist-info/METADATA
application_tracker-0.1.0.dist-info/WHEEL
application_tracker-0.1.0.dist-info/RECORD
